README.md
setup.py
cubeswriter/__init__.py
cubeswriter/helpers.py
cubeswriter/modelers.py
cubeswriter/parsers.py
cubeswriter.egg-info/PKG-INFO
cubeswriter.egg-info/SOURCES.txt
cubeswriter.egg-info/dependency_links.txt
cubeswriter.egg-info/top_level.txt
tests/__init__.py
tests/cubeswriter/__init__.py
tests/cubeswriter/conftest.py
tests/cubeswriter/test_parsers.py