Metadata-Version: 1.0
Name: cubeswriter
Version: 0.0.1
Summary: Cubeswriter is a tool for creating write-layer SQLalchemy models from Cubes model JSON
Home-page: https://github.com/puhrez/CubesWriter.git
Author: Michael Pérez
Author-email: mpuhrez@gmail.com
License: MIT
Keywords: cubes,sql,write-layer,data
Platform: any
